capasm/__init__.py
capasm/assembler.py
capasm/capcommon.py
capasm/captools.py
capasm/globals75.py
capasm/globals85.py
capasm/globals87.py
capasm/globalsnone.py
capasm/ncas.py
capasm-1.0.1.dist-info/METADATA
capasm-1.0.1.dist-info/WHEEL
capasm-1.0.1.dist-info/entry_points.txt
capasm-1.0.1.dist-info/licenses/LICENSE
capasm-1.0.1.dist-info/RECORD
